{
	"configurations" : 
	[
		{
			"directories" : 
			[
				{
					"build" : ".",
					"jsonFile" : "directory-.-Debug-f5ebdc15457944623624.json",
					"minimumCMakeVersion" : 
					{
						"string" : "3.22"
					},
					"projectIndex" : 0,
					"source" : ".",
					"targetIndexes" : 
					[
						0
					]
				}
			],
			"name" : "Debug",
			"projects" : 
			[
				{
					"directoryIndexes" : 
					[
						0
					],
					"name" : "OS_LAB_QUIZ",
					"targetIndexes" : 
					[
						0
					]
				}
			],
			"targets" : 
			[
				{
					"directoryIndex" : 0,
					"id" : "OS_LAB_QUIZ::@6890427a1f51a3e7e1df",
					"jsonFile" : "target-OS_LAB_QUIZ-Debug-07a2295aba0bf9f75f2c.json",
					"name" : "OS_LAB_QUIZ",
					"projectIndex" : 0
				}
			]
		}
	],
	"kind" : "codemodel",
	"paths" : 
	{
		"build" : "/mnt/c/Anas's Data Win/PROGRAMMING/Programs C/OS_LABS/OS_LAB_QUIZ/cmake-build-debug",
		"source" : "/mnt/c/Anas's Data Win/PROGRAMMING/Programs C/OS_LABS/OS_LAB_QUIZ"
	},
	"version" : 
	{
		"major" : 2,
		"minor" : 3
	}
}
